ptdc/__init__.py
ptdc/collector.py
ptdc/streamer.py
ptdc/support.py
ptdc-1.3.6.dist-info/LICENSE
ptdc-1.3.6.dist-info/METADATA
ptdc-1.3.6.dist-info/WHEEL
ptdc-1.3.6.dist-info/top_level.txt
ptdc-1.3.6.dist-info/RECORD
