Metadata-Version: 2.1
Name: ptdc
Version: 1.3.6
Summary: Twitter data collection library
Home-page: https://github.com/lampajr/PTDC/
Author: Andrea Lamparelli
Author-email: lampa9559@gmail.com
License: MIT License
Keywords: twitter api tweepy collection data streaming
Platform: UNKNOWN
Classifier: Development Status :: 3 - Alpha
Classifier: Intended Audience :: Developers
Classifier: Intended Audience :: Science/Research
Classifier: License :: OSI Approved :: MIT License
Classifier: Natural Language :: English
Classifier: Programming Language :: Python :: 3.7
Classifier: Topic :: Software Development :: Libraries :: Python Modules
Requires-Dist: urllib3
Requires-Dist: numpy
Requires-Dist: pandas
Requires-Dist: tweepy
Requires-Dist: simplejson
